CONTRIBUTING.rst
HISTORY.rst
LICENSE.rst
MANIFEST.in
README.rst
setup.cfg
setup.py
docs/Makefile
docs/conf.py
docs/contributing.rst
docs/history.rst
docs/index.rst
docs/installation.rst
docs/make.bat
docs/readme.rst
docs/usage.rst
legacyplatequery/__init__.py
legacyplatequery/api.py
legacyplatequery/client.py
legacyplatequery/legacyplatequery.py
legacyplatequery/utils.py
legacyplatequery/version.py
legacyplatequery.egg-info/PKG-INFO
legacyplatequery.egg-info/SOURCES.txt
legacyplatequery.egg-info/dependency_links.txt
legacyplatequery.egg-info/not-zip-safe
legacyplatequery.egg-info/requires.txt
legacyplatequery.egg-info/top_level.txt
tests/__init__.py
tests/test_api.py
tests/test_legacyplatequery.py