Metadata-Version: 2.1
Name: legacyplatequery
Version: 0.1.1
Summary: Legacyplate Data Query
Home-page: https://github.com/wangweihua/legacyplatequery
Author: Wang Weihua
Author-email: wangwh@czu.cn
Keywords: legacyplatequery
Classifier: Development Status :: 2 - Pre-Alpha
Classifier: Intended Audience :: Developers
Classifier: Natural Language :: English
Classifier: Programming Language :: Python :: 3
Classifier: Programming Language :: Python :: 3.8
Classifier: Programming Language :: Python :: 3.9
Classifier: Programming Language :: Python :: 3.10
Requires-Python: >=3.8
License-File: LICENSE.rst
